odoo/addons/delivery_carrier_option/README.rst
odoo/addons/delivery_carrier_option/__init__.py
odoo/addons/delivery_carrier_option/__manifest__.py
odoo/addons/delivery_carrier_option/i18n/delivery_carrier_option.pot
odoo/addons/delivery_carrier_option/i18n/it.po
odoo/addons/delivery_carrier_option/models/__init__.py
odoo/addons/delivery_carrier_option/models/delivery_carrier.py
odoo/addons/delivery_carrier_option/models/delivery_carrier_option.py
odoo/addons/delivery_carrier_option/models/delivery_carrier_template_option.py
odoo/addons/delivery_carrier_option/models/stock_picking.py
odoo/addons/delivery_carrier_option/readme/CONTRIBUTORS.md
odoo/addons/delivery_carrier_option/readme/DESCRIPTION.md
odoo/addons/delivery_carrier_option/security/ir.model.access.csv
odoo/addons/delivery_carrier_option/static/description/icon.png
odoo/addons/delivery_carrier_option/static/description/index.html
odoo/addons/delivery_carrier_option/tests/__init__.py
odoo/addons/delivery_carrier_option/tests/test_options.py
odoo/addons/delivery_carrier_option/views/delivery_carrier.xml
odoo/addons/delivery_carrier_option/views/delivery_carrier_option.xml
odoo/addons/delivery_carrier_option/views/delivery_carrier_template_option.xml
odoo/addons/delivery_carrier_option/views/stock_picking.xml
odoo_addon_delivery_carrier_option-18.0.1.0.0.6.dist-info/METADATA
odoo_addon_delivery_carrier_option-18.0.1.0.0.6.dist-info/WHEEL
odoo_addon_delivery_carrier_option-18.0.1.0.0.6.dist-info/top_level.txt
odoo_addon_delivery_carrier_option-18.0.1.0.0.6.dist-info/RECORD
